sapcai/__init__.py
sapcai/client.py
sapcai/utils.py
sapcai/apis/__init__.py
sapcai/apis/errors.py
sapcai/apis/build/__init__.py
sapcai/apis/build/build.py
sapcai/apis/build/dialog_conversation.py
sapcai/apis/build/dialog_message.py
sapcai/apis/build/dialog_response.py
sapcai/apis/build/utils.py
sapcai/apis/connect/__init__.py
sapcai/apis/connect/connect.py
sapcai/apis/connect/message.py
sapcai/apis/connect/utils.py
sapcai/apis/connect/models/__init__.py
sapcai/apis/connect/models/message.py
sapcai/apis/request/__init__.py
sapcai/apis/request/analyse.py
sapcai/apis/request/converse.py
sapcai/apis/request/request.py
sapcai/apis/request/utils.py
sapcai/apis/request/models/__init__.py
sapcai/apis/request/models/action.py
sapcai/apis/request/models/conversation.py
sapcai/apis/request/models/entity.py
sapcai/apis/request/models/intent.py
sapcai/apis/request/models/response.py
tests/__init__.py
tests/sapcai/__init__.py
tests/sapcai/test_sapcai.py
sapcai-4.0.0.dist-info/LICENSE
sapcai-4.0.0.dist-info/METADATA
sapcai-4.0.0.dist-info/WHEEL
sapcai-4.0.0.dist-info/top_level.txt
sapcai-4.0.0.dist-info/RECORD
