Metadata-Version: 2.1
Name: sapcai
Version: 4.0.0
Summary: SAP Conversational AI official SDK for python
Home-page: https://github.com/SAPConversationalAI/sdk-python
Author: SAP CAI team
Author-email: UNKNOWN
License: MIT
Keywords: sapcai bot nlp
Platform: UNKNOWN
Requires-Dist: requests (>=2.10)
Requires-Dist: pytest (>=2.9)
Requires-Dist: pytest-cov (>=2.2)
Requires-Dist: responses (>=0.5)
